chatgpt_prompt_wrapper/__init__.py
chatgpt_prompt_wrapper/__version__.py
chatgpt_prompt_wrapper/arg_parser.py
chatgpt_prompt_wrapper/chatgpt_prompt_wrapper.py
chatgpt_prompt_wrapper/chatgpt_prompt_wrapper_exception.py
chatgpt_prompt_wrapper/config.py
chatgpt_prompt_wrapper/log_formatter.py
chatgpt_prompt_wrapper/py.typed
chatgpt_prompt_wrapper/chatgpt/__init__.py
chatgpt_prompt_wrapper/chatgpt/ask.py
chatgpt_prompt_wrapper/chatgpt/chat.py
chatgpt_prompt_wrapper/chatgpt/chatgpt.py
chatgpt_prompt_wrapper/chatgpt/discuss.py
chatgpt_prompt_wrapper/chatgpt/stream.py
chatgpt_prompt_wrapper/cmds/__init__.py
chatgpt_prompt_wrapper/cmds/commands.py
chatgpt_prompt_wrapper/cmds/cost.py
chatgpt_prompt_wrapper/cmds/init.py
chatgpt_prompt_wrapper-0.3.0.dist-info/METADATA
chatgpt_prompt_wrapper-0.3.0.dist-info/WHEEL
chatgpt_prompt_wrapper-0.3.0.dist-info/entry_points.txt
chatgpt_prompt_wrapper-0.3.0.dist-info/licenses/LICENSE
chatgpt_prompt_wrapper-0.3.0.dist-info/RECORD
