Metadata-Version: 2.4
Name: chatgpt-prompt-wrapper
Version: 0.3.0
Summary: CLI tool to wrap ChatGPT Python API.
Project-URL: Repository, https://github.com/rcmdnk/chatgpt-prompt-wrapper
Project-URL: Documentation, https://github.com/rcmdnk/chatgpt-prompt-wrapper
Project-URL: Homepage, https://github.com/rcmdnk/chatgpt-prompt-wrapper
Project-URL: Issue, https://github.com/rcmdnk/chatgpt-prompt-wrapper/issues
Author-email: rcmdnk <rcmdnk@gmail.com>
License-Expression: Apache-2.0
License-File: LICENSE
Keywords: chat,cli,gpt,openai
Classifier: Development Status :: 3 - Alpha
Classifier: Environment :: Console
Classifier: Intended Audience :: Developers
Classifier: Intended Audience :: End Users/Desktop
Classifier: License :: OSI Approved :: Apache Software License
Classifier: Natural Language :: English
Classifier: Operating System :: OS Independent
Classifier: Programming Language :: Python :: 3.9
Classifier: Programming Language :: Python :: 3.10
Classifier: Programming Language :: Python :: 3.11
Classifier: Programming Language :: Python :: 3.12
Classifier: Topic :: Communications :: Chat
Classifier: Topic :: Utilities
Requires-Python: >=3.9
Requires-Dist: conf-finder>=0.2.2
Requires-Dist: inherit-docstring>=0.1.4
Requires-Dist: openai>=1.0.0
Requires-Dist: prompt-toolkit>=3.0.39
Requires-Dist: tiktoken>=0.8.0
Requires-Dist: tomli>=2.0.1; python_version < '3.11'
